rtl.sv
module priority_encoder_4to2 (
    input  wire [3:0] I,
    output reg  [1:0] Y
);

always @(*) begin
    if (I[3])
        Y = 2'b11;
    else if (I[2])
        Y = 2'b10;
    else if (I[1])
        Y = 2'b01;
    else if (I[0])
        Y = 2'b00;
    else
        Y = 2'bxx;   // No input is active
end

endmodule

tb.sv
`timescale 1ns/1ps

module priority_encoder_4to2_tb;

    reg  [3:0] I;
    wire [1:0] Y;

    // Instantiate the Design Under Test (DUT)
    priority_encoder_4to2 DUT (
        .I(I),
        .Y(Y)
    );

    initial begin
        $dumpfile("runs/COOKIE/Simulation/WAVEFORM.vcd");
        $dumpvars(0, priority_encoder_4to2_tb);
        // Display values in the simulation
        $monitor("Time = %0t | I = %b | Y = %b", 
                 $time, I, Y);

        // Test cases
        I = 4'b0000;
        #10;

        I = 4'b0001;
        #10;

        I = 4'b0010;
        #10;

        I = 4'b0011;
        #10;

        I = 4'b0100;
        #10;

        I = 4'b0101;
        #10;

        I = 4'b0110;
        #10;

        I = 4'b0111;
        #10;

        I = 4'b1000;
        #10;

        I = 4'b1001;
        #10;

        I = 4'b1010;
        #10;

        I = 4'b1011;
        #10;

        I = 4'b1100;
        #10;

        I = 4'b1101;
        #10;

        I = 4'b1110;
        #10;

        I = 4'b1111;
        #10;

        $finish;
        
    end

endmodule

WAVEFORM.vcd
$date
	Sun Sep 13 16:11:17 2026
$end
$version
	Icarus Verilog
$end
$timescale
	1ps
$end
$scope module priority_encoder_4to2_tb $end
$var wire 2 ! Y [1:0] $end
$var reg 4 " I [3:0] $end
$scope module DUT $end
$var wire 4 # I [3:0] $end
$var reg 2 $ Y [1:0] $end
$upscope $end
$upscope $end
$enddefinitions $end
$comment Show the parameter values. $end
$dumpall
$end
#0
$dumpvars
bx $
b0 #
b0 "
bx !
$end
#10000
b0 !
b0 $
b1 "
b1 #
#20000
b1 !
b1 $
b10 "
b10 #
#30000
b11 "
b11 #
#40000
b10 !
b10 $
b100 "
b100 #
#50000
b101 "
b101 #
#60000
b110 "
b110 #
#70000
b111 "
b111 #
#80000
b11 !
b11 $
b1000 "
b1000 #
#90000
b1001 "
b1001 #
#100000
b1010 "
b1010 #
#110000
b1011 "
b1011 #
#120000
b1100 "
b1100 #
#130000
b1101 "
b1101 #
#140000
b1110 "
b1110 #
#150000
b1111 "
b1111 #
